testwizard/commands_remotecontrol/SendRCKeyCommand.py
testwizard/commands_remotecontrol/SendRCKeyResult.py
testwizard/commands_remotecontrol/__init__.py
testwizard.commands_remotecontrol-3.8.1.dist-info/LICENSE.txt
testwizard.commands_remotecontrol-3.8.1.dist-info/METADATA
testwizard.commands_remotecontrol-3.8.1.dist-info/WHEEL
testwizard.commands_remotecontrol-3.8.1.dist-info/top_level.txt
testwizard.commands_remotecontrol-3.8.1.dist-info/RECORD
